micro_shared_lib/__init__.py
micro_shared_lib/models.py
micro_shared_lib/utils.py
micro_shared_lib/authentication/__init__.py
micro_shared_lib/authentication/auth.py
micro_shared_lib/authentication/permissions.py
micro_shared_lib-0.0.1.dist-info/LICENSE
micro_shared_lib-0.0.1.dist-info/METADATA
micro_shared_lib-0.0.1.dist-info/WHEEL
micro_shared_lib-0.0.1.dist-info/top_level.txt
micro_shared_lib-0.0.1.dist-info/RECORD
