Metadata-Version: 2.1
Name: micro-shared-lib
Version: 0.0.1
Summary: A shared library used in Microservices
Author-email: Ridwan Yusuf <alabarise@gmail.com>
Project-URL: Homepage, https://github.com/ridwanray/micro_shared_lib
Classifier: Programming Language :: Python :: 3
Classifier: License :: OSI Approved :: MIT License
Classifier: Operating System :: OS Independent
Requires-Python: >=3.9
License-File: LICENSE
